kanjidb_anki/__init__.py
kanjidb_anki/__version__.py
kanjidb_anki/builder/__init__.py
kanjidb_anki/builder/plugins/__init__.py
kanjidb_anki/builder/plugins/ankideck.py
kanjidb_anki-0.1.0.dist-info/LICENSE
kanjidb_anki-0.1.0.dist-info/METADATA
kanjidb_anki-0.1.0.dist-info/WHEEL
kanjidb_anki-0.1.0.dist-info/entry_points.txt
kanjidb_anki-0.1.0.dist-info/top_level.txt
kanjidb_anki-0.1.0.dist-info/RECORD
